setup.py
distributions_wol/Binomialdistribution.py
distributions_wol/Gaussiandistribution.py
distributions_wol/Generaldistribution.py
distributions_wol/__init__.py
distributions_wol.egg-info/PKG-INFO
distributions_wol.egg-info/SOURCES.txt
distributions_wol.egg-info/dependency_links.txt
distributions_wol.egg-info/not-zip-safe
distributions_wol.egg-info/top_level.txt